tokenizer_tools/__init__.py
tokenizer_tools/cli.py
tokenizer_tools/hooks.py
tokenizer_tools/split_data.py
tokenizer_tools/tokenizer_tools.py
tokenizer_tools/conll/__init__.py
tokenizer_tools/conll/entity_vocabulary.py
tokenizer_tools/conll/iterator_reader.py
tokenizer_tools/conll/reader.py
tokenizer_tools/conll/tag_collector.py
tokenizer_tools/conll/writer.py
tokenizer_tools/conllz/__init__.py
tokenizer_tools/conllz/iterator_reader.py
tokenizer_tools/conllz/multiprocess_reader.py
tokenizer_tools/conllz/reader.py
tokenizer_tools/conllz/sentence.py
tokenizer_tools/conllz/writer.py
tokenizer_tools/converter/__init__.py
tokenizer_tools/converter/conllx_to_offset.py
tokenizer_tools/converter/conllx_to_rasa.py
tokenizer_tools/converter/offset_to_sentence.py
tokenizer_tools/converter/sentence_to_offset.py
tokenizer_tools/evaluator/__init__.py
tokenizer_tools/evaluator/offset_evaluator.py
tokenizer_tools/evaluator/tag_level_evaluator.py
tokenizer_tools/evaluator/token/__init__.py
tokenizer_tools/evaluator/token/base_evaluator.py
tokenizer_tools/evaluator/token/tag_level.py
tokenizer_tools/evaluator/token/token_level.py
tokenizer_tools/format_converter/__init__.py
tokenizer_tools/format_converter/corpus_to_rasa_json.py
tokenizer_tools/tagset/BMES.py
tokenizer_tools/tagset/__init__.py
tokenizer_tools/tagset/exceptions.py
tokenizer_tools/tagset/NER/BILUO.py
tokenizer_tools/tagset/NER/IOB.py
tokenizer_tools/tagset/NER/__init__.py
tokenizer_tools/tagset/NER/base_tagset.py
tokenizer_tools/tagset/converter/__init__.py
tokenizer_tools/tagset/converter/offset_to_biluo.py
tokenizer_tools/tagset/offset/__init__.py
tokenizer_tools/tagset/offset/corpus.py
tokenizer_tools/tagset/offset/corpus_diff.py
tokenizer_tools/tagset/offset/corpus_metric.py
tokenizer_tools/tagset/offset/corpus_pb2.py
tokenizer_tools/tagset/offset/corpus_protobuf.py
tokenizer_tools/tagset/offset/corpus_set.py
tokenizer_tools/tagset/offset/corpus_statistics.py
tokenizer_tools/tagset/offset/corpus_stream_reader.py
tokenizer_tools-0.46.1.dist-info/AUTHORS.rst
tokenizer_tools-0.46.1.dist-info/LICENSE
tokenizer_tools-0.46.1.dist-info/METADATA
tokenizer_tools-0.46.1.dist-info/WHEEL
tokenizer_tools-0.46.1.dist-info/entry_points.txt
tokenizer_tools-0.46.1.dist-info/top_level.txt
tokenizer_tools-0.46.1.dist-info/RECORD
