Metadata-Version: 2.1
Name: tokenizer-tools
Version: 0.46.1
Summary: Tools for tokenizer develope and evaluation
Home-page: https://github.com/howlandersonn/tokenizer_tools
Author: Xiaoquan Kong
Author-email: u1mail2me@gmail.com
License: MIT license
Keywords: tokenizer_tools
Platform: UNKNOWN
Classifier: Development Status :: 2 - Pre-Alpha
Classifier: Intended Audience :: Developers
Classifier: License :: OSI Approved :: MIT License
Classifier: Natural Language :: English
Classifier: Programming Language :: Python :: 2
Classifier: Programming Language :: Python :: 2.7
Classifier: Programming Language :: Python :: 3
Classifier: Programming Language :: Python :: 3.5
Classifier: Programming Language :: Python :: 3.6
Classifier: Programming Language :: Python :: 3.7
Requires-Dist: Click (>=6.0)
Requires-Dist: scikit-learn
Requires-Dist: scipy
Requires-Dist: pandas
Requires-Dist: fuzzywuzzy
Requires-Dist: plotly
Requires-Dist: mistletoe
Requires-Dist: tqdm
Requires-Dist: flask
Requires-Dist: elasticsearch-dsl
Requires-Dist: pyahocorasick
